mo_osrs_highscores/__init__.py
mo_osrs_highscores/__version__.py
mo_osrs_highscores/base.py
mo_osrs_highscores/highscores.py
mo_osrs_highscores/rankings.py
mo_osrs_highscores/resources/__init__.py
mo_osrs_highscores/resources/bossslicer.py
mo_osrs_highscores/resources/categories.py
mo_osrs_highscores/resources/category.py
mo_osrs_highscores/resources/dotnotationcreator.py
mo_osrs_highscores/resources/listslicer.py
mo_osrs_highscores/resources/minigameslicer.py
mo_osrs_highscores/resources/skillslicer.py
mo_osrs_highscores/resources/utils.py
tests/__init__.py
tests/test_highscores.py
tests/test_rankings.py
mo_osrs_highscores-1.2.0.dist-info/LICENSE
mo_osrs_highscores-1.2.0.dist-info/METADATA
mo_osrs_highscores-1.2.0.dist-info/WHEEL
mo_osrs_highscores-1.2.0.dist-info/top_level.txt
mo_osrs_highscores-1.2.0.dist-info/RECORD
