Metadata-Version: 2.1
Name: mo-osrs-highscores
Version: 1.2.0
Summary: Simple Wrapper for the OSRS Highscores
Home-page: 
Author: BigMo
Author-email: 
License: MIT License
Classifier: Programming Language :: Python :: 3
Classifier: License :: OSI Approved :: MIT License
Classifier: Operating System :: OS Independent
Requires-Python: >=3.7
License-File: LICENSE
Requires-Dist: requests (==2.27.1)
Requires-Dist: beautifulsoup4 (==4.11.1)
Requires-Dist: addict (==2.4.0)
